safepass/__init__.py
safepass/__main__.py
safepass-1.0.1.dist-info/METADATA
safepass-1.0.1.dist-info/RECORD
safepass-1.0.1.dist-info/WHEEL
safepass-1.0.1.dist-info/entry_points.txt
safepass-1.0.1.dist-info/top_level.txt
