Metadata-Version: 2.1
Name: safepass
Version: 1.0.1
Summary: Check passwords against https://haveibeenpwned.com/API/v2#PwnedPasswords
Home-page: https://github.com/cmccandless/safepass
Author: Corey McCandless
Author-email: crm1994@gmail.com
License: UNKNOWN
Platform: UNKNOWN
Classifier: Programming Language :: Python :: 3
Classifier: License :: OSI Approved :: MIT License
Classifier: Operating System :: OS Independent
Requires-Dist: requests
